[{"resource": [{"timestamp": 1781615716.8292391, "CPU count": 64, "CPU util.": 0.084, "Total mem.": 772625.2, "Used mem.": 17553.82, "Free mem.": 569145.0, "Available mem.": 755071.38, "Mem. util.": 0.02271970937525724, "GPU total mem.": [49140], "GPU free mem.": [48536], "GPU used mem.": [4], "GPU util.": [0.0]}, {"timestamp": 1781615717.5721617, "CPU count": 64, "CPU util.": 0.057, "Total mem.": 772625.2, "Used mem.": 17965.32, "Free mem.": 568727.34, "Available mem.": 754659.87, "Mem. util.": 0.02325230914031797, "GPU total mem.": [49140], "GPU free mem.": [48536], "GPU used mem.": [4], "GPU util.": [0.0]}], "sampling interval": 0.5, "time": 1.0440514087677002, "resource_analysis": {"GPU free mem.": {"max": 48536, "min": 48536, "avg": 48536.0}, "Available mem.": {"max": 755071.38, "min": 754659.87, "avg": 754865.625}, "Free mem.": {"max": 569145.0, "min": 568727.34, "avg": 568936.1699999999}, "CPU util.": {"max": 0.084, "min": 0.057, "avg": 0.07050000000000001}, "GPU used mem.": {"max": 4, "min": 4, "avg": 4.0}, "Mem. util.": {"max": 0.02325230914031797, "min": 0.02271970937525724, "avg": 0.022986009257787605}, "Used mem.": {"max": 17965.32, "min": 17553.82, "avg": 17759.57}, "GPU util.": {"max": 0.0, "min": 0.0, "avg": 0.0}}}, {"resource": [{"timestamp": 1781615718.53924, "CPU count": 64, "CPU util.": 0.079, "Total mem.": 772625.2, "Used mem.": 17651.9, "Free mem.": 569035.86, "Available mem.": 754973.3, "Mem. util.": 0.02284665320261364, "GPU total mem.": [49140], "GPU free mem.": [48536], "GPU used mem.": [4], "GPU util.": [0.0]}, {"timestamp": 1781615719.2227056, "CPU count": 64, "CPU util.": 0.042, "Total mem.": 772625.2, "Used mem.": 17855.9, "Free mem.": 568831.84, "Available mem.": 754769.29, "Mem. util.": 0.023110688080067804, "GPU total mem.": [49140], "GPU free mem.": [48536], "GPU used mem.": [4], "GPU util.": [0.0]}, {"timestamp": 1781615719.9863086, "CPU count": 64, "CPU util.": 0.055999999999999994, "Total mem.": 772625.2, "Used mem.": 17818.41, "Free mem.": 568869.29, "Available mem.": 754806.79, "Mem. util.": 0.023062165199892525, "GPU total mem.": [49140], "GPU free mem.": [48536], "GPU used mem.": [4], "GPU util.": [0.0]}, {"timestamp": 1781615720.7054725, "CPU count": 64, "CPU util.": 0.069, "Total mem.": 772625.2, "Used mem.": 17755.35, "Free mem.": 568932.3, "Available mem.": 754869.85, "Mem. util.": 0.022980547359832425, "GPU total mem.": [49140], "GPU free mem.": [48536], "GPU used mem.": [4], "GPU util.": [0.0]}], "sampling interval": 0.5, "time": 2.787403106689453, "resource_analysis": {"GPU free mem.": {"max": 48536, "min": 48536, "avg": 48536.0}, "Available mem.": {"max": 754973.3, "min": 754769.29, "avg": 754854.8075}, "Free mem.": {"max": 569035.86, "min": 568831.84, "avg": 568917.3225}, "CPU util.": {"max": 0.079, "min": 0.042, "avg": 0.0615}, "GPU used mem.": {"max": 4, "min": 4, "avg": 4.0}, "Mem. util.": {"max": 0.023110688080067804, "min": 0.02284665320261364, "avg": 0.023000013460601598}, "Used mem.": {"max": 17855.9, "min": 17651.9, "avg": 17770.39}, "GPU util.": {"max": 0.0, "min": 0.0, "avg": 0.0}}}, {"resource": [{"timestamp": 1781615721.6026063, "CPU count": 64, "CPU util.": 0.07400000000000001, "Total mem.": 772625.2, "Used mem.": 17707.11, "Free mem.": 568980.6, "Available mem.": 754918.09, "Mem. util.": 0.02291811087704621, "GPU total mem.": [49140], "GPU free mem.": [48536], "GPU used mem.": [4], "GPU util.": [0.0]}, {"timestamp": 1781615722.3576417, "CPU count": 64, "CPU util.": 0.049, "Total mem.": 772625.2, "Used mem.": 18004.77, "Free mem.": 568682.88, "Available mem.": 754620.43, "Mem. util.": 0.023303368826178596, "GPU total mem.": [49140], "GPU free mem.": [48536], "GPU used mem.": [4], "GPU util.": [0.0]}, {"timestamp": 1781615723.1479874, "CPU count": 64, "CPU util.": 0.057, "Total mem.": 772625.2, "Used mem.": 17876.75, "Free mem.": 568810.88, "Available mem.": 754748.45, "Mem. util.": 0.023137673997689956, "GPU total mem.": [49140], "GPU free mem.": [48536], "GPU used mem.": [4], "GPU util.": [0.0]}], "sampling interval": 0.5, "time": 1.8303265571594238, "resource_analysis": {"GPU free mem.": {"max": 48536, "min": 48536, "avg": 48536.0}, "Available mem.": {"max": 754918.09, "min": 754620.43, "avg": 754762.3233333332}, "Free mem.": {"max": 568980.6, "min": 568682.88, "avg": 568824.7866666666}, "CPU util.": {"max": 0.07400000000000001, "min": 0.049, "avg": 0.060000000000000005}, "GPU used mem.": {"max": 4, "min": 4, "avg": 4.0}, "Mem. util.": {"max": 0.023303368826178596, "min": 0.02291811087704621, "avg": 0.023119717900304922}, "Used mem.": {"max": 18004.77, "min": 17707.11, "avg": 17862.876666666667}, "GPU util.": {"max": 0.0, "min": 0.0, "avg": 0.0}}}, {"resource": [{"timestamp": 1781615724.0676978, "CPU count": 64, "CPU util.": 0.07, "Total mem.": 772625.2, "Used mem.": 17725.46, "Free mem.": 568962.16, "Available mem.": 754899.73, "Mem. util.": 0.02294186107313093, "GPU total mem.": [49140], "GPU free mem.": [48536], "GPU used mem.": [4], "GPU util.": [0.0]}, {"timestamp": 1781615724.7693133, "CPU count": 64, "CPU util.": 0.214, "Total mem.": 772625.2, "Used mem.": 17996.43, "Free mem.": 568691.23, "Available mem.": 754628.77, "Mem. util.": 0.023292574459129734, "GPU total mem.": [49140], "GPU free mem.": [47925], "GPU used mem.": [682], "GPU util.": [0.13]}, {"timestamp": 1781615725.4556258, "CPU count": 64, "CPU util.": 0.034, "Total mem.": 772625.2, "Used mem.": 18320.49, "Free mem.": 568367.21, "Available mem.": 754304.71, "Mem. util.": 0.023712001627697366, "GPU total mem.": [49140], "GPU free mem.": [47329], "GPU used mem.": [1212], "GPU util.": [0.08]}], "sampling interval": 0.5, "time": 1.7574944496154785, "resource_analysis": {"GPU free mem.": {"max": 48536, "min": 47329, "avg": 47930.0}, "Available mem.": {"max": 754899.73, "min": 754304.71, "avg": 754611.07}, "Free mem.": {"max": 568962.16, "min": 568367.21, "avg": 568673.5333333333}, "CPU util.": {"max": 0.214, "min": 0.034, "avg": 0.10600000000000002}, "GPU used mem.": {"max": 1212, "min": 4, "avg": 632.6666666666666}, "Mem. util.": {"max": 0.023712001627697366, "min": 0.02294186107313093, "avg": 0.023315479053319346}, "Used mem.": {"max": 18320.49, "min": 17725.46, "avg": 18014.126666666667}, "GPU util.": {"max": 0.13, "min": 0.0, "avg": 0.07}}}, {"resource": [{"timestamp": 1781615726.4200196, "CPU count": 64, "CPU util.": 0.07200000000000001, "Total mem.": 772625.2, "Used mem.": 17751.91, "Free mem.": 568935.91, "Available mem.": 754873.29, "Mem. util.": 0.022976095006996926, "GPU total mem.": [49140], "GPU free mem.": [48153], "GPU used mem.": [388], "GPU util.": [0.0]}, {"timestamp": 1781615727.0957968, "CPU count": 64, "CPU util.": 0.036000000000000004, "Total mem.": 772625.2, "Used mem.": 17867.07, "Free mem.": 568820.6, "Available mem.": 754758.13, "Mem. util.": 0.02312514528389703, "GPU total mem.": [49140], "GPU free mem.": [48153], "GPU used mem.": [388], "GPU util.": [0.0]}, {"timestamp": 1781615727.7732062, "CPU count": 64, "CPU util.": 0.035, "Total mem.": 772625.2, "Used mem.": 18426.82, "Free mem.": 568260.84, "Available mem.": 754198.37, "Mem. util.": 0.023849623336127272, "GPU total mem.": [49140], "GPU free mem.": [48153], "GPU used mem.": [388], "GPU util.": [0.0]}, {"timestamp": 1781615728.4994102, "CPU count": 64, "CPU util.": 0.034, "Total mem.": 772625.2, "Used mem.": 18511.14, "Free mem.": 568176.52, "Available mem.": 754114.05, "Mem. util.": 0.02395875775214166, "GPU total mem.": [49140], "GPU free mem.": [48153], "GPU used mem.": [388], "GPU util.": [0.0]}], "sampling interval": 0.5, "time": 2.5496904850006104, "resource_analysis": {"GPU free mem.": {"max": 48153, "min": 48153, "avg": 48153.0}, "Available mem.": {"max": 754873.29, "min": 754114.05, "avg": 754485.96}, "Free mem.": {"max": 568935.91, "min": 568176.52, "avg": 568548.4675}, "CPU util.": {"max": 0.07200000000000001, "min": 0.034, "avg": 0.044250000000000005}, "GPU used mem.": {"max": 388, "min": 388, "avg": 388.0}, "Mem. util.": {"max": 0.02395875775214166, "min": 0.022976095006996926, "avg": 0.023477405344790724}, "Used mem.": {"max": 18511.14, "min": 17751.91, "avg": 18139.235}, "GPU util.": {"max": 0.0, "min": 0.0, "avg": 0.0}}}, {"resource": [{"timestamp": 1781615729.4148672, "CPU count": 64, "CPU util.": 0.067, "Total mem.": 772625.2, "Used mem.": 17780.89, "Free mem.": 568906.57, "Available mem.": 754844.3, "Mem. util.": 0.023013603491058795, "GPU total mem.": [49140], "GPU free mem.": [48153], "GPU used mem.": [388], "GPU util.": [0.0]}], "sampling interval": 0.5, "time": 0.037831783294677734, "resource_analysis": {"GPU free mem.": {"max": 48153, "min": 48153, "avg": 48153.0}, "Available mem.": {"max": 754844.3, "min": 754844.3, "avg": 754844.3}, "Free mem.": {"max": 568906.57, "min": 568906.57, "avg": 568906.57}, "CPU util.": {"max": 0.067, "min": 0.067, "avg": 0.067}, "GPU used mem.": {"max": 388, "min": 388, "avg": 388.0}, "Mem. util.": {"max": 0.023013603491058795, "min": 0.023013603491058795, "avg": 0.023013603491058795}, "Used mem.": {"max": 17780.89, "min": 17780.89, "avg": 17780.89}, "GPU util.": {"max": 0.0, "min": 0.0, "avg": 0.0}}}, {"resource": [{"timestamp": 1781615730.366083, "CPU count": 64, "CPU util.": 0.065, "Total mem.": 772625.2, "Used mem.": 17792.49, "Free mem.": 568894.96, "Available mem.": 754832.71, "Mem. util.": 0.023028617238992466, "GPU total mem.": [49140], "GPU free mem.": [48153], "GPU used mem.": [388], "GPU util.": [0.0]}, {"timestamp": 1781615731.0759869, "CPU count": 64, "CPU util.": 0.602, "Total mem.": 772625.2, "Used mem.": 17893.04, "Free mem.": 568794.39, "Available mem.": 754732.16, "Mem. util.": 0.02315875795922784, "GPU total mem.": [49140], "GPU free mem.": [48153], "GPU used mem.": [388], "GPU util.": [0.0]}, {"timestamp": 1781615731.6732578, "CPU count": 64, "CPU util.": 0.532, "Total mem.": 772625.2, "Used mem.": 18049.22, "Free mem.": 568638.2, "Available mem.": 754575.97, "Mem. util.": 0.023360899955114072, "GPU total mem.": [49140], "GPU free mem.": [48153], "GPU used mem.": [388], "GPU util.": [0.0]}, {"timestamp": 1781615732.2553906, "CPU count": 64, "CPU util.": 0.59, "Total mem.": 772625.2, "Used mem.": 18190.88, "Free mem.": 568496.55, "Available mem.": 754434.32, "Mem. util.": 0.02354424888031092, "GPU total mem.": [49140], "GPU free mem.": [48153], "GPU used mem.": [388], "GPU util.": [0.0]}, {"timestamp": 1781615732.8425934, "CPU count": 64, "CPU util.": 0.442, "Total mem.": 772625.2, "Used mem.": 18360.06, "Free mem.": 568326.87, "Available mem.": 754264.64, "Mem. util.": 0.023763216628191784, "GPU total mem.": [49140], "GPU free mem.": [48153], "GPU used mem.": [388], "GPU util.": [0.0]}, {"timestamp": 1781615733.4242766, "CPU count": 64, "CPU util.": 0.535, "Total mem.": 772625.2, "Used mem.": 18521.94, "Free mem.": 568165.48, "Available mem.": 754103.25, "Mem. util.": 0.02397273606918335, "GPU total mem.": [49140], "GPU free mem.": [48153], "GPU used mem.": [388], "GPU util.": [0.0]}, {"timestamp": 1781615734.038207, "CPU count": 64, "CPU util.": 0.884, "Total mem.": 772625.2, "Used mem.": 18515.84, "Free mem.": 568171.58, "Available mem.": 754109.36, "Mem. util.": 0.023964840908632025, "GPU total mem.": [49140], "GPU free mem.": [48153], "GPU used mem.": [388], "GPU util.": [0.0]}, {"timestamp": 1781615734.6342263, "CPU count": 64, "CPU util.": 0.845, "Total mem.": 772625.2, "Used mem.": 18530.28, "Free mem.": 568157.14, "Available mem.": 754094.91, "Mem. util.": 0.023983530436232213, "GPU total mem.": [49140], "GPU free mem.": [48153], "GPU used mem.": [388], "GPU util.": [0.0]}, {"timestamp": 1781615735.2401032, "CPU count": 64, "CPU util.": 0.804, "Total mem.": 772625.2, "Used mem.": 18549.31, "Free mem.": 568138.07, "Available mem.": 754075.88, "Mem. util.": 0.02400816074857512, "GPU total mem.": [49140], "GPU free mem.": [48153], "GPU used mem.": [388], "GPU util.": [0.0]}, {"timestamp": 1781615735.8541172, "CPU count": 64, "CPU util.": 0.804, "Total mem.": 772625.2, "Used mem.": 18516.79, "Free mem.": 568170.6, "Available mem.": 754108.41, "Mem. util.": 0.02396607048281625, "GPU total mem.": [49140], "GPU free mem.": [48153], "GPU used mem.": [388], "GPU util.": [0.0]}, {"timestamp": 1781615736.4353552, "CPU count": 64, "CPU util.": 0.435, "Total mem.": 772625.2, "Used mem.": 18576.78, "Free mem.": 568110.08, "Available mem.": 754047.92, "Mem. util.": 0.024043714856828383, "GPU total mem.": [49140], "GPU free mem.": [48153], "GPU used mem.": [388], "GPU util.": [0.0]}, {"timestamp": 1781615737.0253153, "CPU count": 64, "CPU util.": 0.036000000000000004, "Total mem.": 772625.2, "Used mem.": 18810.45, "Free mem.": 567876.89, "Available mem.": 753814.75, "Mem. util.": 0.02434615127748875, "GPU total mem.": [49140], "GPU free mem.": [48153], "GPU used mem.": [388], "GPU util.": [0.0]}, {"timestamp": 1781615737.698738, "CPU count": 64, "CPU util.": 0.446, "Total mem.": 772625.2, "Used mem.": 19462.27, "Free mem.": 567225.07, "Available mem.": 753162.93, "Mem. util.": 0.025189794482499406, "GPU total mem.": [49140], "GPU free mem.": [48153], "GPU used mem.": [388], "GPU util.": [0.0]}, {"timestamp": 1781615738.299293, "CPU count": 64, "CPU util.": 0.035, "Total mem.": 772625.2, "Used mem.": 20482.97, "Free mem.": 566204.37, "Available mem.": 752141.73, "Mem. util.": 0.026510874871800715, "GPU total mem.": [49140], "GPU free mem.": [48153], "GPU used mem.": [388], "GPU util.": [0.0]}, {"timestamp": 1781615739.0764964, "CPU count": 64, "CPU util.": 0.065, "Total mem.": 772625.2, "Used mem.": 21789.77, "Free mem.": 564899.05, "Available mem.": 750838.38, "Mem. util.": 0.02820225123384534, "GPU total mem.": [49140], "GPU free mem.": [48153], "GPU used mem.": [388], "GPU util.": [0.0]}, {"timestamp": 1781615739.7303598, "CPU count": 64, "CPU util.": 0.9179999999999999, "Total mem.": 772625.2, "Used mem.": 21352.75, "Free mem.": 565336.06, "Available mem.": 751274.41, "Mem. util.": 0.027636621223330538, "GPU total mem.": [49140], "GPU free mem.": [47949], "GPU used mem.": [674], "GPU util.": [0.31]}, {"timestamp": 1781615740.3077908, "CPU count": 64, "CPU util.": 0.053, "Total mem.": 772625.2, "Used mem.": 20989.45, "Free mem.": 565697.89, "Available mem.": 751635.75, "Mem. util.": 0.02716640616951143, "GPU total mem.": [49140], "GPU free mem.": [46077], "GPU used mem.": [2464], "GPU util.": [0.38]}], "sampling interval": 0.5, "time": 10.346093654632568, "resource_analysis": {"GPU free mem.": {"max": 48153, "min": 46077, "avg": 48018.882352941175}, "Available mem.": {"max": 754832.71, "min": 750838.38, "avg": 753543.9694117649}, "Free mem.": {"max": 568894.96, "min": 564899.05, "avg": 567606.0735294119}, "CPU util.": {"max": 0.9179999999999999, "min": 0.035, "avg": 0.4759411764705883}, "GPU used mem.": {"max": 2464, "min": 388, "avg": 526.9411764705883}, "Mem. util.": {"max": 0.02820225123384534, "min": 0.023028617238992466, "avg": 0.024696876083681214}, "Used mem.": {"max": 21789.77, "min": 17792.49, "avg": 19081.428823529415}, "GPU util.": {"max": 0.38, "min": 0.0, "avg": 0.04058823529411765}}}]