[{"resource": [{"timestamp": 1781091362.6259916, "CPU count": 64, "CPU util.": 0.028999999999999998, "Total mem.": 772625.21, "Used mem.": 11278.37, "Free mem.": 526108.43, "Available mem.": 761346.84, "Mem. util.": 0.01459746569750164, "GPU total mem.": [49140], "GPU free mem.": [48645], "GPU used mem.": [26], "GPU util.": [0.0]}, {"timestamp": 1781091363.284554, "CPU count": 64, "CPU util.": 0.047, "Total mem.": 772625.21, "Used mem.": 11446.02, "Free mem.": 525940.0, "Available mem.": 761179.2, "Mem. util.": 0.014814453180993151, "GPU total mem.": [49140], "GPU free mem.": [48645], "GPU used mem.": [26], "GPU util.": [0.0]}, {"timestamp": 1781091363.9140418, "CPU count": 64, "CPU util.": 0.046, "Total mem.": 772625.21, "Used mem.": 11478.3, "Free mem.": 525906.5, "Available mem.": 761146.91, "Mem. util.": 0.014856232816943676, "GPU total mem.": [49140], "GPU free mem.": [48645], "GPU used mem.": [26], "GPU util.": [0.0]}], "sampling interval": 0.5, "time": 1.8872497081756592, "resource_analysis": {"Mem. util.": {"max": 0.014856232816943676, "min": 0.01459746569750164, "avg": 0.014756050565146157}, "Used mem.": {"max": 11478.3, "min": 11278.37, "avg": 11400.896666666667}, "CPU util.": {"max": 0.047, "min": 0.028999999999999998, "avg": 0.04066666666666666}, "GPU free mem.": {"max": 48645, "min": 48645, "avg": 48645.0}, "GPU util.": {"max": 0.0, "min": 0.0, "avg": 0.0}, "Free mem.": {"max": 526108.43, "min": 525906.5, "avg": 525984.9766666667}, "Available mem.": {"max": 761346.84, "min": 761146.91, "avg": 761224.3166666668}, "GPU used mem.": {"max": 26, "min": 26, "avg": 26.0}}}, {"resource": [{"timestamp": 1781091364.6913006, "CPU count": 64, "CPU util.": 0.034, "Total mem.": 772625.21, "Used mem.": 11501.51, "Free mem.": 525883.93, "Available mem.": 761123.7, "Mem. util.": 0.014886273255308355, "GPU total mem.": [49140], "GPU free mem.": [48645], "GPU used mem.": [26], "GPU util.": [0.0]}, {"timestamp": 1781091365.3177168, "CPU count": 64, "CPU util.": 0.094, "Total mem.": 772625.21, "Used mem.": 11756.64, "Free mem.": 525628.75, "Available mem.": 760868.57, "Mem. util.": 0.015216485105372112, "GPU total mem.": [49140], "GPU free mem.": [48645], "GPU used mem.": [26], "GPU util.": [0.0]}, {"timestamp": 1781091366.0322127, "CPU count": 64, "CPU util.": 0.207, "Total mem.": 772625.21, "Used mem.": 11754.25, "Free mem.": 525630.52, "Available mem.": 760870.96, "Mem. util.": 0.015213391755622368, "GPU total mem.": [49140], "GPU free mem.": [48645], "GPU used mem.": [26], "GPU util.": [0.0]}, {"timestamp": 1781091366.6838305, "CPU count": 64, "CPU util.": 0.036000000000000004, "Total mem.": 772625.21, "Used mem.": 11741.29, "Free mem.": 525643.4, "Available mem.": 760883.92, "Mem. util.": 0.015196617775389443, "GPU total mem.": [49140], "GPU free mem.": [48645], "GPU used mem.": [26], "GPU util.": [0.0]}], "sampling interval": 0.5, "time": 2.063173294067383, "resource_analysis": {"Mem. util.": {"max": 0.015216485105372112, "min": 0.014886273255308355, "avg": 0.01512819197292307}, "Used mem.": {"max": 11756.64, "min": 11501.51, "avg": 11688.4225}, "CPU util.": {"max": 0.207, "min": 0.034, "avg": 0.09275}, "GPU free mem.": {"max": 48645, "min": 48645, "avg": 48645.0}, "GPU util.": {"max": 0.0, "min": 0.0, "avg": 0.0}, "Free mem.": {"max": 525883.93, "min": 525628.75, "avg": 525696.65}, "Available mem.": {"max": 761123.7, "min": 760868.57, "avg": 760936.7875}, "GPU used mem.": {"max": 26, "min": 26, "avg": 26.0}}}, {"resource": [{"timestamp": 1781091367.4927406, "CPU count": 64, "CPU util.": 0.052000000000000005, "Total mem.": 772625.21, "Used mem.": 11578.35, "Free mem.": 525806.83, "Available mem.": 761046.87, "Mem. util.": 0.014985726391195546, "GPU total mem.": [49140], "GPU free mem.": [48645], "GPU used mem.": [26], "GPU util.": [0.0]}, {"timestamp": 1781091368.155187, "CPU count": 64, "CPU util.": 0.047, "Total mem.": 772625.21, "Used mem.": 11892.27, "Free mem.": 525493.65, "Available mem.": 760732.95, "Mem. util.": 0.015392029467948633, "GPU total mem.": [49140], "GPU free mem.": [48645], "GPU used mem.": [26], "GPU util.": [0.0]}, {"timestamp": 1781091368.8376708, "CPU count": 64, "CPU util.": 0.042, "Total mem.": 772625.21, "Used mem.": 11822.98, "Free mem.": 525562.86, "Available mem.": 760802.23, "Mem. util.": 0.015302348210977998, "GPU total mem.": [49140], "GPU free mem.": [48645], "GPU used mem.": [26], "GPU util.": [0.0]}], "sampling interval": 0.5, "time": 1.5359289646148682, "resource_analysis": {"Mem. util.": {"max": 0.015392029467948633, "min": 0.014985726391195546, "avg": 0.015226701356707393}, "Used mem.": {"max": 11892.27, "min": 11578.35, "avg": 11764.533333333335}, "CPU util.": {"max": 0.052000000000000005, "min": 0.042, "avg": 0.04700000000000001}, "GPU free mem.": {"max": 48645, "min": 48645, "avg": 48645.0}, "GPU util.": {"max": 0.0, "min": 0.0, "avg": 0.0}, "Free mem.": {"max": 525806.83, "min": 525493.65, "avg": 525621.1133333333}, "Available mem.": {"max": 761046.87, "min": 760732.95, "avg": 760860.6833333332}, "GPU used mem.": {"max": 26, "min": 26, "avg": 26.0}}}, {"resource": [{"timestamp": 1781091369.6309114, "CPU count": 64, "CPU util.": 0.049, "Total mem.": 772625.21, "Used mem.": 11599.08, "Free mem.": 525787.4, "Available mem.": 761026.13, "Mem. util.": 0.015012556993836638, "GPU total mem.": [49140], "GPU free mem.": [48645], "GPU used mem.": [26], "GPU util.": [0.0]}, {"timestamp": 1781091370.2400746, "CPU count": 64, "CPU util.": 0.214, "Total mem.": 772625.21, "Used mem.": 12547.84, "Free mem.": 524838.64, "Available mem.": 760077.38, "Mem. util.": 0.016240526244283435, "GPU total mem.": [49140], "GPU free mem.": [48645], "GPU used mem.": [26], "GPU util.": [0.0]}, {"timestamp": 1781091370.9162433, "CPU count": 64, "CPU util.": 0.268, "Total mem.": 772625.21, "Used mem.": 13427.54, "Free mem.": 523958.93, "Available mem.": 759197.67, "Mem. util.": 0.017379111924137193, "GPU total mem.": [49140], "GPU free mem.": [48645], "GPU used mem.": [26], "GPU util.": [0.0]}, {"timestamp": 1781091371.5727725, "CPU count": 64, "CPU util.": 0.267, "Total mem.": 772625.21, "Used mem.": 14495.24, "Free mem.": 522891.23, "Available mem.": 758129.97, "Mem. util.": 0.018761023860456225, "GPU total mem.": [49140], "GPU free mem.": [48645], "GPU used mem.": [26], "GPU util.": [0.0]}, {"timestamp": 1781091372.2477384, "CPU count": 64, "CPU util.": 0.268, "Total mem.": 772625.21, "Used mem.": 15021.31, "Free mem.": 522365.17, "Available mem.": 757603.91, "Mem. util.": 0.019441910263321593, "GPU total mem.": [49140], "GPU free mem.": [48645], "GPU used mem.": [26], "GPU util.": [0.0]}, {"timestamp": 1781091372.9034352, "CPU count": 64, "CPU util.": 0.257, "Total mem.": 772625.21, "Used mem.": 15426.79, "Free mem.": 521959.2, "Available mem.": 757197.45, "Mem. util.": 0.019966718404127663, "GPU total mem.": [49140], "GPU free mem.": [48645], "GPU used mem.": [26], "GPU util.": [0.01]}, {"timestamp": 1781091373.5017502, "CPU count": 64, "CPU util.": 0.263, "Total mem.": 772625.21, "Used mem.": 18219.72, "Free mem.": 519166.75, "Available mem.": 754405.0, "Mem. util.": 0.023581575858753045, "GPU total mem.": [49140], "GPU free mem.": [48645], "GPU used mem.": [26], "GPU util.": [0.0]}, {"timestamp": 1781091374.091001, "CPU count": 64, "CPU util.": 0.268, "Total mem.": 772625.21, "Used mem.": 18670.01, "Free mem.": 518716.46, "Available mem.": 753955.21, "Mem. util.": 0.02416438107164533, "GPU total mem.": [49140], "GPU free mem.": [48645], "GPU used mem.": [26], "GPU util.": [0.0]}, {"timestamp": 1781091374.7198665, "CPU count": 64, "CPU util.": 0.267, "Total mem.": 772625.21, "Used mem.": 19249.79, "Free mem.": 518136.18, "Available mem.": 753374.93, "Mem. util.": 0.024914783715121076, "GPU total mem.": [49140], "GPU free mem.": [48645], "GPU used mem.": [26], "GPU util.": [0.0]}, {"timestamp": 1781091375.4154778, "CPU count": 64, "CPU util.": 0.24, "Total mem.": 772625.21, "Used mem.": 19787.93, "Free mem.": 517598.54, "Available mem.": 752837.29, "Mem. util.": 0.025611292181366953, "GPU total mem.": [49140], "GPU free mem.": [48645], "GPU used mem.": [26], "GPU util.": [0.0]}, {"timestamp": 1781091376.11127, "CPU count": 64, "CPU util.": 0.903, "Total mem.": 772625.21, "Used mem.": 20159.59, "Free mem.": 517226.8, "Available mem.": 752465.62, "Mem. util.": 0.02609232748178124, "GPU total mem.": [49140], "GPU free mem.": [48645], "GPU used mem.": [26], "GPU util.": [0.0]}, {"timestamp": 1781091376.7774417, "CPU count": 64, "CPU util.": 0.65, "Total mem.": 772625.21, "Used mem.": 14255.15, "Free mem.": 523145.79, "Available mem.": 758393.69, "Mem. util.": 0.018450278110909688, "GPU total mem.": [49140], "GPU free mem.": [48645], "GPU used mem.": [26], "GPU util.": [0.0]}, {"timestamp": 1781091377.38352, "CPU count": 64, "CPU util.": 0.231, "Total mem.": 772625.21, "Used mem.": 12482.55, "Free mem.": 524903.6, "Available mem.": 760142.67, "Mem. util.": 0.016156022141705677, "GPU total mem.": [49140], "GPU free mem.": [48645], "GPU used mem.": [26], "GPU util.": [0.0]}, {"timestamp": 1781091378.0129712, "CPU count": 64, "CPU util.": 0.26899999999999996, "Total mem.": 772625.21, "Used mem.": 13294.75, "Free mem.": 524091.38, "Available mem.": 759330.46, "Mem. util.": 0.017207243341179613, "GPU total mem.": [49140], "GPU free mem.": [48645], "GPU used mem.": [26], "GPU util.": [0.0]}, {"timestamp": 1781091378.715806, "CPU count": 64, "CPU util.": 0.26899999999999996, "Total mem.": 772625.21, "Used mem.": 14483.25, "Free mem.": 522902.88, "Available mem.": 758141.96, "Mem. util.": 0.01874550534016357, "GPU total mem.": [49140], "GPU free mem.": [48645], "GPU used mem.": [26], "GPU util.": [0.0]}, {"timestamp": 1781091379.3705804, "CPU count": 64, "CPU util.": 0.267, "Total mem.": 772625.21, "Used mem.": 15046.47, "Free mem.": 522339.17, "Available mem.": 757577.27, "Mem. util.": 0.019474474564452796, "GPU total mem.": [49140], "GPU free mem.": [48645], "GPU used mem.": [26], "GPU util.": [0.0]}, {"timestamp": 1781091380.0279248, "CPU count": 64, "CPU util.": 0.255, "Total mem.": 772625.21, "Used mem.": 15238.01, "Free mem.": 522147.6, "Available mem.": 757386.71, "Mem. util.": 0.019722382602555773, "GPU total mem.": [49140], "GPU free mem.": [48645], "GPU used mem.": [26], "GPU util.": [0.0]}, {"timestamp": 1781091380.6188018, "CPU count": 64, "CPU util.": 0.263, "Total mem.": 772625.21, "Used mem.": 17903.83, "Free mem.": 519481.78, "Available mem.": 754720.89, "Mem. util.": 0.023172723033461465, "GPU total mem.": [49140], "GPU free mem.": [48645], "GPU used mem.": [26], "GPU util.": [0.0]}, {"timestamp": 1781091381.2034974, "CPU count": 64, "CPU util.": 0.262, "Total mem.": 772625.21, "Used mem.": 18537.51, "Free mem.": 518848.59, "Available mem.": 754087.21, "Mem. util.": 0.023992887832381238, "GPU total mem.": [49140], "GPU free mem.": [48645], "GPU used mem.": [26], "GPU util.": [0.0]}, {"timestamp": 1781091381.8763983, "CPU count": 64, "CPU util.": 0.265, "Total mem.": 772625.21, "Used mem.": 19128.11, "Free mem.": 518257.98, "Available mem.": 753497.1, "Mem. util.": 0.02475729467848972, "GPU total mem.": [49140], "GPU free mem.": [48645], "GPU used mem.": [26], "GPU util.": [0.0]}, {"timestamp": 1781091382.5525022, "CPU count": 64, "CPU util.": 0.242, "Total mem.": 772625.21, "Used mem.": 19577.32, "Free mem.": 517808.23, "Available mem.": 753047.41, "Mem. util.": 0.02533870205969593, "GPU total mem.": [49140], "GPU free mem.": [48645], "GPU used mem.": [26], "GPU util.": [0.0]}], "sampling interval": 0.5, "time": 13.188600778579712, "resource_analysis": {"Mem. util.": {"max": 0.02609232748178124, "min": 0.015012556993836638, "avg": 0.020865891509705987}, "Used mem.": {"max": 20159.59, "min": 11599.08, "avg": 16121.513809523809}, "CPU util.": {"max": 0.903, "min": 0.049, "avg": 0.297}, "GPU free mem.": {"max": 48645, "min": 48645, "avg": 48645.0}, "GPU util.": {"max": 0.01, "min": 0.0, "avg": 0.0004761904761904762}, "Free mem.": {"max": 525787.4, "min": 517226.8, "avg": 521265.34761904756}, "Available mem.": {"max": 761026.13, "min": 752465.62, "avg": 756504.5680952382}, "GPU used mem.": {"max": 26, "min": 26, "avg": 26.0}}}, {"resource": [{"timestamp": 1781091383.4009848, "CPU count": 64, "CPU util.": 0.18899999999999997, "Total mem.": 772625.21, "Used mem.": 11340.09, "Free mem.": 526045.93, "Available mem.": 761285.13, "Mem. util.": 0.01467734918978375, "GPU total mem.": [49140], "GPU free mem.": [48645], "GPU used mem.": [26], "GPU util.": [0.0]}, {"timestamp": 1781091384.0213006, "CPU count": 64, "CPU util.": 0.196, "Total mem.": 772625.21, "Used mem.": 12298.98, "Free mem.": 525086.71, "Available mem.": 760325.74, "Mem. util.": 0.015918429583730513, "GPU total mem.": [49140], "GPU free mem.": [48645], "GPU used mem.": [26], "GPU util.": [0.0]}, {"timestamp": 1781091384.7390676, "CPU count": 64, "CPU util.": 0.252, "Total mem.": 772625.21, "Used mem.": 13223.73, "Free mem.": 524162.45, "Available mem.": 759401.49, "Mem. util.": 0.01711532296493406, "GPU total mem.": [49140], "GPU free mem.": [48645], "GPU used mem.": [26], "GPU util.": [0.0]}, {"timestamp": 1781091385.392315, "CPU count": 64, "CPU util.": 0.254, "Total mem.": 772625.21, "Used mem.": 14233.83, "Free mem.": 523152.32, "Available mem.": 758391.38, "Mem. util.": 0.018422683877995647, "GPU total mem.": [49140], "GPU free mem.": [48645], "GPU used mem.": [26], "GPU util.": [0.0]}, {"timestamp": 1781091386.0227911, "CPU count": 64, "CPU util.": 0.251, "Total mem.": 772625.21, "Used mem.": 14724.29, "Free mem.": 522661.36, "Available mem.": 757900.44, "Mem. util.": 0.019057480663878416, "GPU total mem.": [49140], "GPU free mem.": [48645], "GPU used mem.": [26], "GPU util.": [0.0]}, {"timestamp": 1781091386.7675633, "CPU count": 64, "CPU util.": 0.24100000000000002, "Total mem.": 772625.21, "Used mem.": 15170.04, "Free mem.": 522216.1, "Available mem.": 757455.18, "Mem. util.": 0.01963440980653479, "GPU total mem.": [49140], "GPU free mem.": [48645], "GPU used mem.": [26], "GPU util.": [0.0]}, {"timestamp": 1781091387.3702896, "CPU count": 64, "CPU util.": 0.242, "Total mem.": 772625.21, "Used mem.": 17810.14, "Free mem.": 519576.0, "Available mem.": 754815.07, "Mem. util.": 0.023051461134694272, "GPU total mem.": [49140], "GPU free mem.": [48645], "GPU used mem.": [26], "GPU util.": [0.0]}, {"timestamp": 1781091387.9633343, "CPU count": 64, "CPU util.": 0.252, "Total mem.": 772625.21, "Used mem.": 18178.88, "Free mem.": 519207.27, "Available mem.": 754446.34, "Mem. util.": 0.02352871711240176, "GPU total mem.": [49140], "GPU free mem.": [48645], "GPU used mem.": [26], "GPU util.": [0.0]}, {"timestamp": 1781091388.5731053, "CPU count": 64, "CPU util.": 0.248, "Total mem.": 772625.21, "Used mem.": 18752.68, "Free mem.": 518633.46, "Available mem.": 753872.53, "Mem. util.": 0.024271379910060144, "GPU total mem.": [49140], "GPU free mem.": [48645], "GPU used mem.": [26], "GPU util.": [0.0]}, {"timestamp": 1781091389.2813675, "CPU count": 64, "CPU util.": 0.23800000000000002, "Total mem.": 772625.21, "Used mem.": 19212.81, "Free mem.": 518173.33, "Available mem.": 753411.91, "Mem. util.": 0.02486692092275892, "GPU total mem.": [49140], "GPU free mem.": [48645], "GPU used mem.": [26], "GPU util.": [0.0]}, {"timestamp": 1781091389.9951358, "CPU count": 64, "CPU util.": 0.237, "Total mem.": 772625.21, "Used mem.": 19365.07, "Free mem.": 518021.07, "Available mem.": 753260.15, "Mem. util.": 0.025063989304723828, "GPU total mem.": [49140], "GPU free mem.": [48645], "GPU used mem.": [26], "GPU util.": [0.0]}, {"timestamp": 1781091390.663539, "CPU count": 64, "CPU util.": 0.23800000000000002, "Total mem.": 772625.21, "Used mem.": 19942.89, "Free mem.": 517443.25, "Available mem.": 752682.32, "Mem. util.": 0.02581185514254706, "GPU total mem.": [49140], "GPU free mem.": [48645], "GPU used mem.": [26], "GPU util.": [0.0]}, {"timestamp": 1781091391.3452966, "CPU count": 64, "CPU util.": 0.23399999999999999, "Total mem.": 772625.21, "Used mem.": 20709.78, "Free mem.": 516675.77, "Available mem.": 751914.45, "Mem. util.": 0.02680443212563566, "GPU total mem.": [49140], "GPU free mem.": [48571], "GPU used mem.": [138], "GPU util.": [0.02]}, {"timestamp": 1781091392.2996356, "CPU count": 64, "CPU util.": 0.154, "Total mem.": 772625.21, "Used mem.": 22244.38, "Free mem.": 515141.65, "Available mem.": 750380.34, "Mem. util.": 0.028790647408463415, "GPU total mem.": [49140], "GPU free mem.": [38889], "GPU used mem.": [10192], "GPU util.": [0.95]}, {"timestamp": 1781091393.0189195, "CPU count": 64, "CPU util.": 0.134, "Total mem.": 772625.21, "Used mem.": 12046.77, "Free mem.": 525339.09, "Available mem.": 760578.45, "Mem. util.": 0.015591997056373557, "GPU total mem.": [49140], "GPU free mem.": [48645], "GPU used mem.": [26], "GPU util.": [0.8]}, {"timestamp": 1781091393.797367, "CPU count": 64, "CPU util.": 0.151, "Total mem.": 772625.21, "Used mem.": 12361.15, "Free mem.": 525024.68, "Available mem.": 760264.06, "Mem. util.": 0.015998895505881825, "GPU total mem.": [49140], "GPU free mem.": [48645], "GPU used mem.": [26], "GPU util.": [0.0]}, {"timestamp": 1781091394.5187201, "CPU count": 64, "CPU util.": 0.252, "Total mem.": 772625.21, "Used mem.": 13285.44, "Free mem.": 524100.39, "Available mem.": 759339.78, "Mem. util.": 0.01719519351433019, "GPU total mem.": [49140], "GPU free mem.": [48645], "GPU used mem.": [26], "GPU util.": [0.0]}, {"timestamp": 1781091395.1986072, "CPU count": 64, "CPU util.": 0.251, "Total mem.": 772625.21, "Used mem.": 14376.12, "Free mem.": 523009.7, "Available mem.": 758249.09, "Mem. util.": 0.01860684820263631, "GPU total mem.": [49140], "GPU free mem.": [48645], "GPU used mem.": [26], "GPU util.": [0.0]}, {"timestamp": 1781091395.8651674, "CPU count": 64, "CPU util.": 0.252, "Total mem.": 772625.21, "Used mem.": 14904.34, "Free mem.": 522481.46, "Available mem.": 757720.88, "Mem. util.": 0.01929051732598785, "GPU total mem.": [49140], "GPU free mem.": [48645], "GPU used mem.": [26], "GPU util.": [0.0]}, {"timestamp": 1781091396.5872052, "CPU count": 64, "CPU util.": 0.244, "Total mem.": 772625.21, "Used mem.": 16038.49, "Free mem.": 521347.3, "Available mem.": 756586.23, "Mem. util.": 0.020758434739658573, "GPU total mem.": [49140], "GPU free mem.": [48645], "GPU used mem.": [26], "GPU util.": [0.0]}, {"timestamp": 1781091397.1794453, "CPU count": 64, "CPU util.": 0.24600000000000002, "Total mem.": 772625.21, "Used mem.": 17948.07, "Free mem.": 519437.72, "Available mem.": 754677.14, "Mem. util.": 0.0232299823610467, "GPU total mem.": [49140], "GPU free mem.": [48645], "GPU used mem.": [26], "GPU util.": [0.0]}, {"timestamp": 1781091397.7697194, "CPU count": 64, "CPU util.": 0.253, "Total mem.": 772625.21, "Used mem.": 18293.25, "Free mem.": 519092.55, "Available mem.": 754331.97, "Mem. util.": 0.02367674489938013, "GPU total mem.": [49140], "GPU free mem.": [48645], "GPU used mem.": [26], "GPU util.": [0.0]}, {"timestamp": 1781091398.363948, "CPU count": 64, "CPU util.": 0.247, "Total mem.": 772625.21, "Used mem.": 18873.79, "Free mem.": 518512.01, "Available mem.": 753751.43, "Mem. util.": 0.02442813120219052, "GPU total mem.": [49140], "GPU free mem.": [48645], "GPU used mem.": [26], "GPU util.": [0.0]}, {"timestamp": 1781091398.989932, "CPU count": 64, "CPU util.": 0.204, "Total mem.": 772625.21, "Used mem.": 19209.13, "Free mem.": 518176.66, "Available mem.": 753416.08, "Mem. util.": 0.02486215794071747, "GPU total mem.": [49140], "GPU free mem.": [48645], "GPU used mem.": [26], "GPU util.": [0.0]}], "sampling interval": 0.5, "time": 15.882153034210205, "resource_analysis": {"Mem. util.": {"max": 0.028790647408463415, "min": 0.01467734918978375, "avg": 0.021277249245681057}, "Used mem.": {"max": 22244.38, "min": 11340.09, "avg": 16439.33916666667}, "CPU util.": {"max": 0.254, "min": 0.134, "avg": 0.2275}, "GPU free mem.": {"max": 48645, "min": 38889, "avg": 48235.416666666664}, "GPU util.": {"max": 0.95, "min": 0.0, "avg": 0.07375}, "Free mem.": {"max": 526045.93, "min": 515141.65, "avg": 520946.5929166668}, "Available mem.": {"max": 761285.13, "min": 750380.34, "avg": 756185.7325}, "GPU used mem.": {"max": 10192, "min": 26, "avg": 454.25}}}, {"resource": [{"timestamp": 1781091399.7442262, "CPU count": 64, "CPU util.": 0.201, "Total mem.": 772625.21, "Used mem.": 11418.45, "Free mem.": 525967.29, "Available mem.": 761206.77, "Mem. util.": 0.014778769644340238, "GPU total mem.": [49140], "GPU free mem.": [48645], "GPU used mem.": [26], "GPU util.": [0.0]}, {"timestamp": 1781091400.3816097, "CPU count": 64, "CPU util.": 0.184, "Total mem.": 772625.21, "Used mem.": 12326.5, "Free mem.": 525059.09, "Available mem.": 760298.22, "Mem. util.": 0.015954048405953516, "GPU total mem.": [49140], "GPU free mem.": [48645], "GPU used mem.": [26], "GPU util.": [0.0]}, {"timestamp": 1781091401.096062, "CPU count": 64, "CPU util.": 0.237, "Total mem.": 772625.21, "Used mem.": 13209.01, "Free mem.": 524177.07, "Available mem.": 759415.71, "Mem. util.": 0.01709627103676827, "GPU total mem.": [49140], "GPU free mem.": [48645], "GPU used mem.": [26], "GPU util.": [0.0]}, {"timestamp": 1781091401.7658758, "CPU count": 64, "CPU util.": 0.235, "Total mem.": 772625.21, "Used mem.": 14124.88, "Free mem.": 523261.2, "Available mem.": 758500.34, "Mem. util.": 0.018281671135219623, "GPU total mem.": [49140], "GPU free mem.": [48645], "GPU used mem.": [26], "GPU util.": [0.0]}, {"timestamp": 1781091402.4769926, "CPU count": 64, "CPU util.": 0.237, "Total mem.": 772625.21, "Used mem.": 14625.54, "Free mem.": 522760.05, "Available mem.": 757998.69, "Mem. util.": 0.018929669664804236, "GPU total mem.": [49140], "GPU free mem.": [48645], "GPU used mem.": [26], "GPU util.": [0.0]}, {"timestamp": 1781091403.215774, "CPU count": 64, "CPU util.": 0.228, "Total mem.": 772625.21, "Used mem.": 15505.63, "Free mem.": 521879.96, "Available mem.": 757118.11, "Mem. util.": 0.020068760117211294, "GPU total mem.": [49140], "GPU free mem.": [48645], "GPU used mem.": [26], "GPU util.": [0.01]}, {"timestamp": 1781091403.8088684, "CPU count": 64, "CPU util.": 0.231, "Total mem.": 772625.21, "Used mem.": 17526.25, "Free mem.": 519859.34, "Available mem.": 755098.47, "Mem. util.": 0.02268402554454572, "GPU total mem.": [49140], "GPU free mem.": [48645], "GPU used mem.": [26], "GPU util.": [0.0]}, {"timestamp": 1781091404.3999026, "CPU count": 64, "CPU util.": 0.237, "Total mem.": 772625.21, "Used mem.": 17833.01, "Free mem.": 519553.07, "Available mem.": 754792.21, "Mem. util.": 0.023081061514935552, "GPU total mem.": [49140], "GPU free mem.": [48645], "GPU used mem.": [26], "GPU util.": [0.0]}, {"timestamp": 1781091405.011604, "CPU count": 64, "CPU util.": 0.233, "Total mem.": 772625.21, "Used mem.": 18439.21, "Free mem.": 518946.87, "Available mem.": 754186.5, "Mem. util.": 0.023865659263176256, "GPU total mem.": [49140], "GPU free mem.": [48645], "GPU used mem.": [26], "GPU util.": [0.0]}, {"timestamp": 1781091405.711038, "CPU count": 64, "CPU util.": 0.19, "Total mem.": 772625.21, "Used mem.": 18774.05, "Free mem.": 518612.03, "Available mem.": 753851.17, "Mem. util.": 0.024299038857404098, "GPU total mem.": [49140], "GPU free mem.": [48645], "GPU used mem.": [26], "GPU util.": [0.0]}, {"timestamp": 1781091406.4076161, "CPU count": 64, "CPU util.": 0.222, "Total mem.": 772625.21, "Used mem.": 18882.23, "Free mem.": 518503.85, "Available mem.": 753742.99, "Mem. util.": 0.02443905499795949, "GPU total mem.": [49140], "GPU free mem.": [48645], "GPU used mem.": [26], "GPU util.": [0.0]}, {"timestamp": 1781091407.0521774, "CPU count": 64, "CPU util.": 0.221, "Total mem.": 772625.21, "Used mem.": 19380.85, "Free mem.": 518005.22, "Available mem.": 753244.36, "Mem. util.": 0.02508441317880373, "GPU total mem.": [49140], "GPU free mem.": [48645], "GPU used mem.": [26], "GPU util.": [0.0]}, {"timestamp": 1781091407.6818771, "CPU count": 64, "CPU util.": 0.215, "Total mem.": 772625.21, "Used mem.": 19928.48, "Free mem.": 517457.5, "Available mem.": 752696.74, "Mem. util.": 0.025793204443846713, "GPU total mem.": [49140], "GPU free mem.": [48645], "GPU used mem.": [26], "GPU util.": [0.0]}], "sampling interval": 0.5, "time": 8.349042892456055, "resource_analysis": {"Mem. util.": {"max": 0.025793204443846713, "min": 0.014778769644340238, "avg": 0.021104280600382205}, "Used mem.": {"max": 19928.48, "min": 11418.45, "avg": 16305.699230769233}, "CPU util.": {"max": 0.237, "min": 0.184, "avg": 0.22084615384615386}, "GPU free mem.": {"max": 48645, "min": 48645, "avg": 48645.0}, "GPU util.": {"max": 0.01, "min": 0.0, "avg": 0.0007692307692307692}, "Free mem.": {"max": 525967.29, "min": 517457.5, "avg": 521080.19538461533}, "Available mem.": {"max": 761206.77, "min": 752696.74, "avg": 756319.2523076923}, "GPU used mem.": {"max": 26, "min": 26, "avg": 26.0}}}, {"resource": [{"timestamp": 1781091408.461759, "CPU count": 64, "CPU util.": 0.20199999999999999, "Total mem.": 772625.21, "Used mem.": 11403.22, "Free mem.": 525982.81, "Available mem.": 761221.99, "Mem. util.": 0.014759057628989351, "GPU total mem.": [49140], "GPU free mem.": [48645], "GPU used mem.": [26], "GPU util.": [0.0]}], "sampling interval": 0.5, "time": 0.09954953193664551, "resource_analysis": {"Mem. util.": {"max": 0.014759057628989351, "min": 0.014759057628989351, "avg": 0.014759057628989351}, "Used mem.": {"max": 11403.22, "min": 11403.22, "avg": 11403.22}, "CPU util.": {"max": 0.20199999999999999, "min": 0.20199999999999999, "avg": 0.20199999999999999}, "GPU free mem.": {"max": 48645, "min": 48645, "avg": 48645.0}, "GPU util.": {"max": 0.0, "min": 0.0, "avg": 0.0}, "Free mem.": {"max": 525982.81, "min": 525982.81, "avg": 525982.81}, "Available mem.": {"max": 761221.99, "min": 761221.99, "avg": 761221.99}, "GPU used mem.": {"max": 26, "min": 26, "avg": 26.0}}}, {"resource": [{"timestamp": 1781091409.2946186, "CPU count": 64, "CPU util.": 0.19899999999999998, "Total mem.": 772625.21, "Used mem.": 11414.6, "Free mem.": 525971.17, "Available mem.": 761210.37, "Mem. util.": 0.014773786633237092, "GPU total mem.": [49140], "GPU free mem.": [48645], "GPU used mem.": [26], "GPU util.": [0.0]}], "sampling interval": 0.5, "time": 0.014262914657592773, "resource_analysis": {"Mem. util.": {"max": 0.014773786633237092, "min": 0.014773786633237092, "avg": 0.014773786633237092}, "Used mem.": {"max": 11414.6, "min": 11414.6, "avg": 11414.6}, "CPU util.": {"max": 0.19899999999999998, "min": 0.19899999999999998, "avg": 0.19899999999999998}, "GPU free mem.": {"max": 48645, "min": 48645, "avg": 48645.0}, "GPU util.": {"max": 0.0, "min": 0.0, "avg": 0.0}, "Free mem.": {"max": 525971.17, "min": 525971.17, "avg": 525971.17}, "Available mem.": {"max": 761210.37, "min": 761210.37, "avg": 761210.37}, "GPU used mem.": {"max": 26, "min": 26, "avg": 26.0}}}, {"resource": [{"timestamp": 1781091410.0618923, "CPU count": 64, "CPU util.": 0.196, "Total mem.": 772625.21, "Used mem.": 11411.36, "Free mem.": 525974.64, "Available mem.": 761213.86, "Mem. util.": 0.01476959313817886, "GPU total mem.": [49140], "GPU free mem.": [48645], "GPU used mem.": [26], "GPU util.": [0.0]}], "sampling interval": 0.5, "time": 0.014358282089233398, "resource_analysis": {"Mem. util.": {"max": 0.01476959313817886, "min": 0.01476959313817886, "avg": 0.01476959313817886}, "Used mem.": {"max": 11411.36, "min": 11411.36, "avg": 11411.36}, "CPU util.": {"max": 0.196, "min": 0.196, "avg": 0.196}, "GPU free mem.": {"max": 48645, "min": 48645, "avg": 48645.0}, "GPU util.": {"max": 0.0, "min": 0.0, "avg": 0.0}, "Free mem.": {"max": 525974.64, "min": 525974.64, "avg": 525974.64}, "Available mem.": {"max": 761213.86, "min": 761213.86, "avg": 761213.86}, "GPU used mem.": {"max": 26, "min": 26, "avg": 26.0}}}]