[{"resource": [{"timestamp": 1781588350.8206165, "CPU count": 64, "CPU util.": 0.146, "Total mem.": 772625.21, "Used mem.": 40940.75, "Free mem.": 94271.86, "Available mem.": 726568.49, "Mem. util.": 0.05298914592755782, "GPU total mem.": [49140], "GPU free mem.": [4180], "GPU used mem.": [44491], "GPU util.": [0.0]}, {"timestamp": 1781588351.4621065, "CPU count": 64, "CPU util.": 0.14300000000000002, "Total mem.": 772625.21, "Used mem.": 40787.53, "Free mem.": 94425.59, "Available mem.": 726722.29, "Mem. util.": 0.05279083502853861, "GPU total mem.": [49140], "GPU free mem.": [4180], "GPU used mem.": [44491], "GPU util.": [0.0]}, {"timestamp": 1781588352.158198, "CPU count": 64, "CPU util.": 0.149, "Total mem.": 772625.21, "Used mem.": 40665.9, "Free mem.": 94546.62, "Available mem.": 726842.91, "Mem. util.": 0.05263341070633717, "GPU total mem.": [49140], "GPU free mem.": [4180], "GPU used mem.": [44491], "GPU util.": [0.0]}], "sampling interval": 0.5, "time": 1.7045385837554932, "resource_analysis": {"GPU used mem.": {"max": 44491, "min": 44491, "avg": 44491.0}, "GPU util.": {"max": 0.0, "min": 0.0, "avg": 0.0}, "Available mem.": {"max": 726842.91, "min": 726568.49, "avg": 726711.23}, "CPU util.": {"max": 0.149, "min": 0.14300000000000002, "avg": 0.14600000000000002}, "Used mem.": {"max": 40940.75, "min": 40665.9, "avg": 40798.06}, "Mem. util.": {"max": 0.05298914592755782, "min": 0.05263341070633717, "avg": 0.052804463887477865}, "Free mem.": {"max": 94546.62, "min": 94271.86, "avg": 94414.69}, "GPU free mem.": {"max": 4180, "min": 4180, "avg": 4180.0}}}, {"resource": [{"timestamp": 1781588352.990029, "CPU count": 64, "CPU util.": 0.145, "Total mem.": 772625.21, "Used mem.": 40949.92, "Free mem.": 94262.29, "Available mem.": 726558.91, "Mem. util.": 0.05300101455400349, "GPU total mem.": [49140], "GPU free mem.": [4180], "GPU used mem.": [44491], "GPU util.": [0.0]}, {"timestamp": 1781588353.6682267, "CPU count": 64, "CPU util.": 0.205, "Total mem.": 772625.21, "Used mem.": 41830.42, "Free mem.": 93383.2, "Available mem.": 725679.37, "Mem. util.": 0.054140635664735814, "GPU total mem.": [49140], "GPU free mem.": [4180], "GPU used mem.": [44491], "GPU util.": [0.0]}, {"timestamp": 1781588354.363082, "CPU count": 64, "CPU util.": 0.297, "Total mem.": 772625.21, "Used mem.": 44236.03, "Free mem.": 90976.58, "Available mem.": 723272.77, "Mem. util.": 0.057254189259498794, "GPU total mem.": [49140], "GPU free mem.": [4180], "GPU used mem.": [44491], "GPU util.": [0.0]}, {"timestamp": 1781588355.0628648, "CPU count": 64, "CPU util.": 0.29100000000000004, "Total mem.": 772625.21, "Used mem.": 43445.97, "Free mem.": 91775.32, "Available mem.": 724077.11, "Mem. util.": 0.05623162360958944, "GPU total mem.": [49140], "GPU free mem.": [4180], "GPU used mem.": [44491], "GPU util.": [0.0]}, {"timestamp": 1781588355.728226, "CPU count": 64, "CPU util.": 0.927, "Total mem.": 772625.21, "Used mem.": 44921.82, "Free mem.": 90291.52, "Available mem.": 722587.97, "Mem. util.": 0.058141799437271796, "GPU total mem.": [49140], "GPU free mem.": [4180], "GPU used mem.": [44491], "GPU util.": [0.0]}, {"timestamp": 1781588356.4369993, "CPU count": 64, "CPU util.": 0.9990000000000001, "Total mem.": 772625.21, "Used mem.": 43920.99, "Free mem.": 91292.82, "Available mem.": 723591.26, "Mem. util.": 0.0568464365795157, "GPU total mem.": [49140], "GPU free mem.": [4180], "GPU used mem.": [44491], "GPU util.": [0.0]}, {"timestamp": 1781588357.1473098, "CPU count": 64, "CPU util.": 0.968, "Total mem.": 772625.21, "Used mem.": 44903.79, "Free mem.": 90309.52, "Available mem.": 722605.99, "Mem. util.": 0.0581184634138459, "GPU total mem.": [49140], "GPU free mem.": [4180], "GPU used mem.": [44491], "GPU util.": [0.0]}, {"timestamp": 1781588357.9187028, "CPU count": 64, "CPU util.": 0.9990000000000001, "Total mem.": 772625.21, "Used mem.": 45455.05, "Free mem.": 89757.25, "Available mem.": 722055.21, "Mem. util.": 0.05883195294650042, "GPU total mem.": [49140], "GPU free mem.": [4180], "GPU used mem.": [44491], "GPU util.": [0.0]}, {"timestamp": 1781588358.5491476, "CPU count": 64, "CPU util.": 0.9990000000000001, "Total mem.": 772625.21, "Used mem.": 44264.46, "Free mem.": 90947.84, "Available mem.": 723245.8, "Mem. util.": 0.057290985884346175, "GPU total mem.": [49140], "GPU free mem.": [4180], "GPU used mem.": [44491], "GPU util.": [0.0]}, {"timestamp": 1781588359.151086, "CPU count": 64, "CPU util.": 0.995, "Total mem.": 772625.21, "Used mem.": 44806.63, "Free mem.": 90404.65, "Available mem.": 722702.18, "Mem. util.": 0.05799271033364288, "GPU total mem.": [49140], "GPU free mem.": [4180], "GPU used mem.": [44491], "GPU util.": [0.0]}, {"timestamp": 1781588359.8465424, "CPU count": 64, "CPU util.": 0.995, "Total mem.": 772625.21, "Used mem.": 45890.75, "Free mem.": 89321.48, "Available mem.": 721619.53, "Mem. util.": 0.059395874488744685, "GPU total mem.": [49140], "GPU free mem.": [4180], "GPU used mem.": [44491], "GPU util.": [0.0]}, {"timestamp": 1781588360.5690136, "CPU count": 64, "CPU util.": 0.9990000000000001, "Total mem.": 772625.21, "Used mem.": 43674.44, "Free mem.": 91538.51, "Available mem.": 723835.84, "Mem. util.": 0.05652732972562467, "GPU total mem.": [49140], "GPU free mem.": [4180], "GPU used mem.": [44491], "GPU util.": [0.0]}, {"timestamp": 1781588361.3193731, "CPU count": 64, "CPU util.": 0.9990000000000001, "Total mem.": 772625.21, "Used mem.": 45960.94, "Free mem.": 89251.46, "Available mem.": 721548.85, "Mem. util.": 0.059486720605453715, "GPU total mem.": [49140], "GPU free mem.": [4180], "GPU used mem.": [44491], "GPU util.": [0.0]}, {"timestamp": 1781588361.9345307, "CPU count": 64, "CPU util.": 0.992, "Total mem.": 772625.21, "Used mem.": 44283.17, "Free mem.": 90929.71, "Available mem.": 723226.12, "Mem. util.": 0.057315202024018866, "GPU total mem.": [49140], "GPU free mem.": [4180], "GPU used mem.": [44491], "GPU util.": [0.0]}, {"timestamp": 1781588362.6590507, "CPU count": 64, "CPU util.": 0.9990000000000001, "Total mem.": 772625.21, "Used mem.": 43866.57, "Free mem.": 91345.81, "Available mem.": 723642.72, "Mem. util.": 0.056776001394000596, "GPU total mem.": [49140], "GPU free mem.": [4180], "GPU used mem.": [44491], "GPU util.": [0.0]}, {"timestamp": 1781588363.3193424, "CPU count": 64, "CPU util.": 0.996, "Total mem.": 772625.21, "Used mem.": 45678.31, "Free mem.": 89534.08, "Available mem.": 721830.5, "Mem. util.": 0.05912091581893891, "GPU total mem.": [49140], "GPU free mem.": [4180], "GPU used mem.": [44491], "GPU util.": [0.0]}, {"timestamp": 1781588364.024585, "CPU count": 64, "CPU util.": 1.0, "Total mem.": 772625.21, "Used mem.": 44074.42, "Free mem.": 91138.46, "Available mem.": 723435.86, "Mem. util.": 0.05704501927914053, "GPU total mem.": [49140], "GPU free mem.": [4180], "GPU used mem.": [44491], "GPU util.": [0.0]}, {"timestamp": 1781588364.7090614, "CPU count": 64, "CPU util.": 0.9990000000000001, "Total mem.": 772625.21, "Used mem.": 45257.57, "Free mem.": 89954.31, "Available mem.": 722251.73, "Mem. util.": 0.058576356834124016, "GPU total mem.": [49140], "GPU free mem.": [4180], "GPU used mem.": [44491], "GPU util.": [0.0]}, {"timestamp": 1781588365.350661, "CPU count": 64, "CPU util.": 0.986, "Total mem.": 772625.21, "Used mem.": 45340.03, "Free mem.": 89870.86, "Available mem.": 722169.27, "Mem. util.": 0.058683083871933196, "GPU total mem.": [49140], "GPU free mem.": [4180], "GPU used mem.": [44491], "GPU util.": [0.0]}, {"timestamp": 1781588365.9619887, "CPU count": 64, "CPU util.": 0.8190000000000001, "Total mem.": 772625.21, "Used mem.": 44606.39, "Free mem.": 90605.38, "Available mem.": 722902.41, "Mem. util.": 0.0577335419847354, "GPU total mem.": [49140], "GPU free mem.": [4180], "GPU used mem.": [44491], "GPU util.": [0.0]}, {"timestamp": 1781588366.5435054, "CPU count": 64, "CPU util.": 0.256, "Total mem.": 772625.21, "Used mem.": 42141.26, "Free mem.": 93070.5, "Available mem.": 725368.77, "Mem. util.": 0.05454295233260639, "GPU total mem.": [49140], "GPU free mem.": [4180], "GPU used mem.": [44491], "GPU util.": [0.0]}], "sampling interval": 0.5, "time": 13.926771879196167, "resource_analysis": {"GPU used mem.": {"max": 44491, "min": 44491, "avg": 44491.0}, "GPU util.": {"max": 0.0, "min": 0.0, "avg": 0.0}, "Available mem.": {"max": 726558.91, "min": 721548.85, "avg": 723248.008095238}, "CPU util.": {"max": 1.0, "min": 0.145, "avg": 0.8030952380952383}, "Used mem.": {"max": 45960.94, "min": 40949.92, "avg": 44262.33}, "Mem. util.": {"max": 0.059486720605453715, "min": 0.05300101455400349, "avg": 0.057288229049631975}, "Free mem.": {"max": 94262.29, "min": 89251.46, "avg": 90950.55000000002}, "GPU free mem.": {"max": 4180, "min": 4180, "avg": 4180.0}}}, {"resource": [{"timestamp": 1781588367.284974, "CPU count": 64, "CPU util.": 0.6729999999999999, "Total mem.": 772625.21, "Used mem.": 40724.89, "Free mem.": 94486.8, "Available mem.": 726784.91, "Mem. util.": 0.05270976079074614, "GPU total mem.": [49140], "GPU free mem.": [4180], "GPU used mem.": [44491], "GPU util.": [0.0]}, {"timestamp": 1781588368.0428934, "CPU count": 64, "CPU util.": 0.214, "Total mem.": 772625.21, "Used mem.": 41723.61, "Free mem.": 93487.62, "Available mem.": 725785.67, "Mem. util.": 0.05400239269955999, "GPU total mem.": [49140], "GPU free mem.": [4180], "GPU used mem.": [44491], "GPU util.": [0.0]}, {"timestamp": 1781588368.761303, "CPU count": 64, "CPU util.": 0.308, "Total mem.": 772625.21, "Used mem.": 43884.07, "Free mem.": 91327.32, "Available mem.": 723624.72, "Mem. util.": 0.05679865144446944, "GPU total mem.": [49140], "GPU free mem.": [4180], "GPU used mem.": [44491], "GPU util.": [0.0]}, {"timestamp": 1781588369.445122, "CPU count": 64, "CPU util.": 0.268, "Total mem.": 772625.21, "Used mem.": 43393.27, "Free mem.": 91820.9, "Available mem.": 724121.43, "Mem. util.": 0.05616341460046327, "GPU total mem.": [49140], "GPU free mem.": [4180], "GPU used mem.": [44491], "GPU util.": [0.0]}, {"timestamp": 1781588370.1094365, "CPU count": 64, "CPU util.": 0.162, "Total mem.": 772625.21, "Used mem.": 42450.19, "Free mem.": 92761.5, "Available mem.": 725059.6, "Mem. util.": 0.05494279690925436, "GPU total mem.": [49140], "GPU free mem.": [4180], "GPU used mem.": [44491], "GPU util.": [0.0]}], "sampling interval": 0.5, "time": 2.851682662963867, "resource_analysis": {"GPU used mem.": {"max": 44491, "min": 44491, "avg": 44491.0}, "GPU util.": {"max": 0.0, "min": 0.0, "avg": 0.0}, "Available mem.": {"max": 726784.91, "min": 723624.72, "avg": 725075.2660000001}, "CPU util.": {"max": 0.6729999999999999, "min": 0.162, "avg": 0.32499999999999996}, "Used mem.": {"max": 43884.07, "min": 40724.89, "avg": 42435.206}, "Mem. util.": {"max": 0.05679865144446944, "min": 0.05270976079074614, "avg": 0.054923403288898644}, "Free mem.": {"max": 94486.8, "min": 91327.32, "avg": 92776.82800000001}, "GPU free mem.": {"max": 4180, "min": 4180, "avg": 4180.0}}}, {"resource": [{"timestamp": 1781588370.8626835, "CPU count": 64, "CPU util.": 0.596, "Total mem.": 772625.21, "Used mem.": 40417.72, "Free mem.": 94794.46, "Available mem.": 727092.58, "Mem. util.": 0.052312194162031034, "GPU total mem.": [49140], "GPU free mem.": [4180], "GPU used mem.": [44491], "GPU util.": [0.0]}, {"timestamp": 1781588371.5154192, "CPU count": 64, "CPU util.": 0.217, "Total mem.": 772625.21, "Used mem.": 41750.62, "Free mem.": 93459.19, "Available mem.": 725758.19, "Mem. util.": 0.054037351434597904, "GPU total mem.": [49140], "GPU free mem.": [4180], "GPU used mem.": [44491], "GPU util.": [0.0]}], "sampling interval": 0.5, "time": 0.8770303726196289, "resource_analysis": {"GPU used mem.": {"max": 44491, "min": 44491, "avg": 44491.0}, "GPU util.": {"max": 0.0, "min": 0.0, "avg": 0.0}, "Available mem.": {"max": 727092.58, "min": 725758.19, "avg": 726425.385}, "CPU util.": {"max": 0.596, "min": 0.217, "avg": 0.4065}, "Used mem.": {"max": 41750.62, "min": 40417.72, "avg": 41084.17}, "Mem. util.": {"max": 0.054037351434597904, "min": 0.052312194162031034, "avg": 0.053174772798314465}, "Free mem.": {"max": 94794.46, "min": 93459.19, "avg": 94126.82500000001}, "GPU free mem.": {"max": 4180, "min": 4180, "avg": 4180.0}}}]