[{"resource": [{"timestamp": 1781622295.8734226, "CPU count": 64, "CPU util.": 0.07200000000000001, "Total mem.": 772625.2, "Used mem.": 12295.04, "Free mem.": 573161.42, "Available mem.": 760330.16, "Mem. util.": 0.01591333029261795, "GPU total mem.": [49140], "GPU free mem.": [48536], "GPU used mem.": [4], "GPU util.": [0.0]}, {"timestamp": 1781622296.5231776, "CPU count": 64, "CPU util.": 0.019, "Total mem.": 772625.2, "Used mem.": 12455.59, "Free mem.": 573000.87, "Available mem.": 760169.11, "Mem. util.": 0.016121128329751606, "GPU total mem.": [49140], "GPU free mem.": [48536], "GPU used mem.": [4], "GPU util.": [0.0]}], "sampling interval": 0.5, "time": 1.2472248077392578, "resource_analysis": {"GPU util.": {"max": 0.0, "min": 0.0, "avg": 0.0}, "CPU util.": {"max": 0.07200000000000001, "min": 0.019, "avg": 0.045500000000000006}, "GPU used mem.": {"max": 4, "min": 4, "avg": 4.0}, "Free mem.": {"max": 573161.42, "min": 573000.87, "avg": 573081.145}, "Available mem.": {"max": 760330.16, "min": 760169.11, "avg": 760249.635}, "Used mem.": {"max": 12455.59, "min": 12295.04, "avg": 12375.315}, "GPU free mem.": {"max": 48536, "min": 48536, "avg": 48536.0}, "Mem. util.": {"max": 0.016121128329751606, "min": 0.01591333029261795, "avg": 0.01601722931118478}}}, {"resource": [{"timestamp": 1781622297.6176882, "CPU count": 64, "CPU util.": 0.067, "Total mem.": 772625.2, "Used mem.": 12404.42, "Free mem.": 573041.66, "Available mem.": 760220.77, "Mem. util.": 0.01605489958132352, "GPU total mem.": [49140], "GPU free mem.": [48536], "GPU used mem.": [4], "GPU util.": [0.0]}, {"timestamp": 1781622298.3064795, "CPU count": 64, "CPU util.": 0.02, "Total mem.": 772625.2, "Used mem.": 12580.82, "Free mem.": 572864.77, "Available mem.": 760043.88, "Mem. util.": 0.016283212093004474, "GPU total mem.": [49140], "GPU free mem.": [48536], "GPU used mem.": [4], "GPU util.": [0.0]}, {"timestamp": 1781622298.9946513, "CPU count": 64, "CPU util.": 0.052000000000000005, "Total mem.": 772625.2, "Used mem.": 12436.37, "Free mem.": 573009.64, "Available mem.": 760188.82, "Mem. util.": 0.016096252102571856, "GPU total mem.": [49140], "GPU free mem.": [48536], "GPU used mem.": [4], "GPU util.": [0.0]}, {"timestamp": 1781622299.674058, "CPU count": 64, "CPU util.": 0.034, "Total mem.": 772625.2, "Used mem.": 12748.95, "Free mem.": 572697.02, "Available mem.": 759876.25, "Mem. util.": 0.016500820837839617, "GPU total mem.": [49140], "GPU free mem.": [48536], "GPU used mem.": [4], "GPU util.": [0.0]}, {"timestamp": 1781622300.4094107, "CPU count": 64, "CPU util.": 0.046, "Total mem.": 772625.2, "Used mem.": 12523.48, "Free mem.": 572922.48, "Available mem.": 760101.71, "Mem. util.": 0.016208997583822014, "GPU total mem.": [49140], "GPU free mem.": [48536], "GPU used mem.": [4], "GPU util.": [0.0]}], "sampling interval": 0.5, "time": 3.42849063873291, "resource_analysis": {"GPU util.": {"max": 0.0, "min": 0.0, "avg": 0.0}, "CPU util.": {"max": 0.067, "min": 0.02, "avg": 0.043800000000000006}, "GPU used mem.": {"max": 4, "min": 4, "avg": 4.0}, "Free mem.": {"max": 573041.66, "min": 572697.02, "avg": 572907.1140000001}, "Available mem.": {"max": 760220.77, "min": 759876.25, "avg": 760086.286}, "Used mem.": {"max": 12748.95, "min": 12404.42, "avg": 12538.807999999999}, "GPU free mem.": {"max": 48536, "min": 48536, "avg": 48536.0}, "Mem. util.": {"max": 0.016500820837839617, "min": 0.01605489958132352, "avg": 0.016228836439712298}}}, {"resource": [{"timestamp": 1781622301.3802605, "CPU count": 64, "CPU util.": 0.06, "Total mem.": 772625.2, "Used mem.": 12453.4, "Free mem.": 572992.51, "Available mem.": 760171.79, "Mem. util.": 0.01611829383768482, "GPU total mem.": [49140], "GPU free mem.": [48536], "GPU used mem.": [4], "GPU util.": [0.0]}, {"timestamp": 1781622302.0404763, "CPU count": 64, "CPU util.": 0.019, "Total mem.": 772625.2, "Used mem.": 12589.88, "Free mem.": 572856.18, "Available mem.": 760035.32, "Mem. util.": 0.016294938347856114, "GPU total mem.": [49140], "GPU free mem.": [48536], "GPU used mem.": [4], "GPU util.": [0.0]}, {"timestamp": 1781622302.7758868, "CPU count": 64, "CPU util.": 0.061, "Total mem.": 772625.2, "Used mem.": 12506.68, "Free mem.": 572939.36, "Available mem.": 760118.52, "Mem. util.": 0.016187253535090495, "GPU total mem.": [49140], "GPU free mem.": [48536], "GPU used mem.": [4], "GPU util.": [0.0]}, {"timestamp": 1781622303.4401531, "CPU count": 64, "CPU util.": 0.023, "Total mem.": 772625.2, "Used mem.": 12655.77, "Free mem.": 572790.21, "Available mem.": 759969.42, "Mem. util.": 0.016380219024696583, "GPU total mem.": [49140], "GPU free mem.": [48536], "GPU used mem.": [4], "GPU util.": [0.0]}], "sampling interval": 0.5, "time": 2.2735042572021484, "resource_analysis": {"GPU util.": {"max": 0.0, "min": 0.0, "avg": 0.0}, "CPU util.": {"max": 0.061, "min": 0.019, "avg": 0.04075}, "GPU used mem.": {"max": 4, "min": 4, "avg": 4.0}, "Free mem.": {"max": 572992.51, "min": 572790.21, "avg": 572894.565}, "Available mem.": {"max": 760171.79, "min": 759969.42, "avg": 760073.7625}, "Used mem.": {"max": 12655.77, "min": 12453.4, "avg": 12551.432499999999}, "GPU free mem.": {"max": 48536, "min": 48536, "avg": 48536.0}, "Mem. util.": {"max": 0.016380219024696583, "min": 0.01611829383768482, "avg": 0.016245176186332002}}}, {"resource": [{"timestamp": 1781622304.4264169, "CPU count": 64, "CPU util.": 0.055999999999999994, "Total mem.": 772625.2, "Used mem.": 12462.2, "Free mem.": 572983.89, "Available mem.": 760163.0, "Mem. util.": 0.016129683577496567, "GPU total mem.": [49140], "GPU free mem.": [48536], "GPU used mem.": [4], "GPU util.": [0.0]}], "sampling interval": 0.5, "time": 0.13829755783081055, "resource_analysis": {"GPU util.": {"max": 0.0, "min": 0.0, "avg": 0.0}, "CPU util.": {"max": 0.055999999999999994, "min": 0.055999999999999994, "avg": 0.055999999999999994}, "GPU used mem.": {"max": 4, "min": 4, "avg": 4.0}, "Free mem.": {"max": 572983.89, "min": 572983.89, "avg": 572983.89}, "Available mem.": {"max": 760163.0, "min": 760163.0, "avg": 760163.0}, "Used mem.": {"max": 12462.2, "min": 12462.2, "avg": 12462.2}, "GPU free mem.": {"max": 48536, "min": 48536, "avg": 48536.0}, "Mem. util.": {"max": 0.016129683577496567, "min": 0.016129683577496567, "avg": 0.016129683577496567}}}, {"resource": [{"timestamp": 1781622305.336664, "CPU count": 64, "CPU util.": 0.054000000000000006, "Total mem.": 772625.2, "Used mem.": 12464.97, "Free mem.": 572981.11, "Available mem.": 760160.23, "Mem. util.": 0.016133268756960036, "GPU total mem.": [49140], "GPU free mem.": [48536], "GPU used mem.": [4], "GPU util.": [0.0]}], "sampling interval": 0.5, "time": 0.012498140335083008, "resource_analysis": {"GPU util.": {"max": 0.0, "min": 0.0, "avg": 0.0}, "CPU util.": {"max": 0.054000000000000006, "min": 0.054000000000000006, "avg": 0.054000000000000006}, "GPU used mem.": {"max": 4, "min": 4, "avg": 4.0}, "Free mem.": {"max": 572981.11, "min": 572981.11, "avg": 572981.11}, "Available mem.": {"max": 760160.23, "min": 760160.23, "avg": 760160.23}, "Used mem.": {"max": 12464.97, "min": 12464.97, "avg": 12464.97}, "GPU free mem.": {"max": 48536, "min": 48536, "avg": 48536.0}, "Mem. util.": {"max": 0.016133268756960036, "min": 0.016133268756960036, "avg": 0.016133268756960036}}}, {"resource": [{"timestamp": 1781622306.292644, "CPU count": 64, "CPU util.": 0.051, "Total mem.": 772625.2, "Used mem.": 12478.92, "Free mem.": 572967.15, "Available mem.": 760146.27, "Mem. util.": 0.01615132408313889, "GPU total mem.": [49140], "GPU free mem.": [48536], "GPU used mem.": [4], "GPU util.": [0.0]}], "sampling interval": 0.5, "time": 0.013415098190307617, "resource_analysis": {"GPU util.": {"max": 0.0, "min": 0.0, "avg": 0.0}, "CPU util.": {"max": 0.051, "min": 0.051, "avg": 0.051}, "GPU used mem.": {"max": 4, "min": 4, "avg": 4.0}, "Free mem.": {"max": 572967.15, "min": 572967.15, "avg": 572967.15}, "Available mem.": {"max": 760146.27, "min": 760146.27, "avg": 760146.27}, "Used mem.": {"max": 12478.92, "min": 12478.92, "avg": 12478.92}, "GPU free mem.": {"max": 48536, "min": 48536, "avg": 48536.0}, "Mem. util.": {"max": 0.01615132408313889, "min": 0.01615132408313889, "avg": 0.01615132408313889}}}, {"resource": [{"timestamp": 1781622307.2463887, "CPU count": 64, "CPU util.": 0.049, "Total mem.": 772625.2, "Used mem.": 12471.66, "Free mem.": 572974.41, "Available mem.": 760153.54, "Mem. util.": 0.016141927547794196, "GPU total mem.": [49140], "GPU free mem.": [48536], "GPU used mem.": [4], "GPU util.": [0.0]}], "sampling interval": 0.5, "time": 0.1234133243560791, "resource_analysis": {"GPU util.": {"max": 0.0, "min": 0.0, "avg": 0.0}, "CPU util.": {"max": 0.049, "min": 0.049, "avg": 0.049}, "GPU used mem.": {"max": 4, "min": 4, "avg": 4.0}, "Free mem.": {"max": 572974.41, "min": 572974.41, "avg": 572974.41}, "Available mem.": {"max": 760153.54, "min": 760153.54, "avg": 760153.54}, "Used mem.": {"max": 12471.66, "min": 12471.66, "avg": 12471.66}, "GPU free mem.": {"max": 48536, "min": 48536, "avg": 48536.0}, "Mem. util.": {"max": 0.016141927547794196, "min": 0.016141927547794196, "avg": 0.016141927547794196}}}]